embed_files/__init__.py
embed_files/py.typed
embed_files-1.1.0.dist-info/LICENSE
embed_files-1.1.0.dist-info/METADATA
embed_files-1.1.0.dist-info/WHEEL
embed_files-1.1.0.dist-info/entry_points.txt
embed_files-1.1.0.dist-info/RECORD
